Workbook

Sheet README
A1: KPI Dictionary & Data Quality Contract: Retail Orders
A3: Dataset | B3: retail-orders-raw.csv (12 raw rows, 11 distinct orders; Learning Kit, Course Access and Mentor Session sales in INR)
A4: Decision owner | B4: Head of Growth & Revenue Operations (assumed role; replace with the real name)
A5: Purpose | B5: Turn the ambiguous request 'how are our orders doing?' into 10 measurable KPIs, and state what trustworthy data means with testable checks.
A7: Sheet | B7: What it contains
A8: KPI_Dictionary | B8: 10 KPIs, each with formula, grain, filters, owner, refresh cadence, edge cases and a live sample value.
A9: KPI_Check | B9: Recomputes every KPI with live Excel formulas on Clean_Data and compares with the Python notebook (should all say OK).
A10: DQ_Checks | B10: 18 executable checks across completeness, uniqueness, validity, consistency and freshness, with thresholds, severity and results.
A11: Severity_Escalation | B11: What happens when a check fails at P1 / P2 / P3.
A12: Clean_Data | B12: Rows that passed cleaning (deduplicated, normalized). KPI formulas read this sheet.
A13: Quarantine | B13: Rows excluded from KPIs, with the exact reason.
A14: Raw_Data | B14: Untouched copy of the source file, all values as text.
A16: Colour code | B16: Blue font = hardcoded value (raw data, notebook results, thresholds). Black = formula. Green = link to another sheet.
... A19: Companion files | B19: data_profile_notebook.ipynb (executable profile) and data_quality_contract.md (the contract).

Sheet KPI_Dictionary
A1: KPI ID | B1: KPI name | C1: Business question | D1: Formula | E1: Grain | F1: Filters / inclusion rules | G1: Unit | H1: Owner | I1: Refresh cadence | J1: Source columns | K1: Sample value (clean data) | L1: Edge cases & notes
A2: KPI-01 | B2: Order Count | C2: How many valid orders did we receive? | D2: COUNT(DISTINCT order_id) | E2: 1 row = 1 order | F2: Clean set only (deduplicated, no blocking defects). All payment statuses included. | G2: orders | H2: Retail Operations Manager | I2: Daily, 06:00 IST | J2: order_id | K2: =KPI_Check!C2 -> 6 | L2: Excludes quarantined rows; their count is tracked in KPI-10.
A3: KPI-02 | B3: Gross Merchandise Value (GMV) | C3: What is the booked value of orders before discounts? | D3: SUM(quantity x unit_price) | E3: Order | F3: Clean set; payment_status <> 'Failed'. Pending and Refunded stay in (they were booked). | G3: INR | H3: Head of Growth & Revenue Ops | I3: Daily, 06:00 IST | J3: quantity, unit_price, payment_status | K3: =KPI_Check!C3 -> 9291 | L3: Failed payments never completed, so they are not booked value.
A4: KPI-03 | B4: Discount Amount | C4: How much money did we give away in discounts? | D4: SUM(quantity x unit_price x discount_pct / 100) | E4: Order | F4: Same filter as GMV (clean set, status <> 'Failed'). | G4: INR | H4: Pricing & Promotions Lead | I4: Daily, 06:00 IST | J4: quantity, unit_price, discount_pct | K4: =KPI_Check!C4 -> 729.35 | L4: discount_pct must be 0-100 and present; a missing discount quarantines the row.
A5: KPI-04 | B5: Discount Rate | C5: What share of GMV is given away as discount? | D5: Discount Amount / GMV | E5: Whole period (ratio of two sums) | F5: Same filter as GMV. | G5: % | H5: Pricing & Promotions Lead | I5: Daily, 06:00 IST | J5: KPI-03, KPI-02 | K5: =KPI_Check!C5 -> 0.0785007 | L5: Ratio of sums, NOT the average of per-order discount_pct. Returns 0 if GMV = 0.
A6: KPI-05 | B6: Net Revenue | C6: How much money have we actually kept from completed sales? | D6: SUM(quantity x unit_price x (1 - discount_pct / 100)) | E6: Order | F6: Clean set; payment_status = 'Paid' only. Refunded, Pending and Failed excluded. | G6: INR | H6: Head of Growth & Revenue Ops | I6: Daily, 06:00 IST | J6: quantity, unit_price, discount_pct, payment_status | K6: =KPI_Check!C6 -> 6013.35 | L6: Primary revenue KPI. A refund moves an order from Paid to Refunded, so revenue drops automatically.
A7: KPI-06 | B7: Average Order Value (AOV) | C7: How much does a typical paid order bring in? | D7: Net Revenue / COUNT(DISTINCT order_id where status = 'Paid') | E7: Order | F7: Clean set; Paid orders only. | G7: INR per order | H7: Growth Analyst | I7: Daily, 06:00 IST | J7: KPI-05, order_id, payment_status | K7: =KPI_Check!C7 -> 1503.3375 | L7: Returns 0 when there are no paid orders.
A8: KPI-07 | B8: Units per Order | C8: How many items are in a typical paid order? | D8: SUM(quantity) / COUNT(DISTINCT order_id) for Paid orders | E8: Order | F8: Clean set; Paid orders only. | G8: units | H8: Growth Analyst | I8: Daily, 06:00 IST | J8: quantity, order_id, payment_status | K8: =KPI_Check!C8 -> 1.75 | L8: Mentor Sessions and Course Access are usually 1 unit, so mix affects this.
A9: KPI-08 | B9: Payment Success Rate | C9: Of the payments that reached a final outcome, how many succeeded? | D9: COUNT(Paid) / (COUNT(Paid) + COUNT(Failed)) | E9: Order | F9: Clean set. Pending excluded from the denominator (no outcome yet); Refunded excluded. | G9: % | H9: Payments Operations Lead | I9: Daily, 06:00 IST | J9: payment_status, order_id | K9: =KPI_Check!C9 -> 0.8 | L9: A drop signals gateway or checkout problems; review alongside Pending backlog.
A10: KPI-09 | B10: Refund Rate | C10: How many completed sales were refunded? | D10: COUNT(Refunded) / (COUNT(Paid) + COUNT(Refunded)) | E10: Order | F10: Clean set. Denominator = all orders that were ever successfully paid. | G10: % | H10: Customer Support Lead | I10: Weekly, Monday 07:00 IST (refunds lag) | J10: payment_status, order_id | K10: =KPI_Check!C10 -> 0.2 | L10: Order-count based. A value-based version can be added if refund sizes vary a lot.
A11: KPI-10 | B11: Data Quality Pass Rate | C11: What share of orders is trustworthy enough to report on? | D11: COUNT(DISTINCT order_id in clean set) / COUNT(DISTINCT order_id in raw) | E11: Order | F11: Raw extract before cleaning vs. clean set after the contract rules. | G11: % | H11: Data Platform Owner | I11: Every load (daily, 06:00 IST) | J11: order_id (raw and clean) | K11: =KPI_Check!C11 -> 0.54545455 | L11: Contract target: >= 98% in production. This sample is far below target.

Sheet KPI_Check
A1: KPI ID | B1: KPI name | C1: Workbook value (live formula) | D1: Notebook value (data_profile_notebook.ipynb) | E1: Match? | F1: Display format
A2: KPI-01 | B2: Order Count | C2: =COUNTA(Clean_Data!$A$2:$A$500) -> 6 | D2: 6 | E2: =IF(ABS(C2-D2)<0.001,"OK","CHECK") -> OK | F2: 0
A3: KPI-02 | B3: Gross Merchandise Value (GMV) | C3: =SUMIFS(Clean_Data!$K$2:$K$500,Clean_Data!$I$2:$I$500,"<>Failed") -> 9291 | D3: 9291 | E3: =IF(ABS(C3-D3)<0.001,"OK","CHECK") -> OK | F3: #,##0.00
A4: KPI-03 | B4: Discount Amount | C4: =SUMIFS(Clean_Data!$L$2:$L$500,Clean_Data!$I$2:$I$500,"<>Failed") -> 729.35 | D4: 729.35 | E4: =IF(ABS(C4-D4)<0.001,"OK","CHECK") -> OK | F4: #,##0.00
A5: KPI-04 | B5: Discount Rate | C5: =IF(C3=0,0,C4/C3) -> 0.0785007 | D5: 0.0785 | E5: =IF(ABS(C5-D5)<0.001,"OK","CHECK") -> OK | F5: 0.0%
A6: KPI-05 | B6: Net Revenue | C6: =SUMIFS(Clean_Data!$M$2:$M$500,Clean_Data!$I$2:$I$500,"Paid") -> 6013.35 | D6: 6013.35 | E6: =IF(ABS(C6-D6)<0.001,"OK","CHECK") -> OK | F6: #,##0.00
A7: KPI-06 | B7: Average Order Value (AOV) | C7: =IF(COUNTIFS(Clean_Data!$I$2:$I$500,"Paid")=0,0,C6/COUNTIFS(Clean_Data!$I$2:$I$500,"Paid")) -> 1503.3375 | D7: 1503.3375 | E7: =IF(ABS(C7-D7)<0.001,"OK","CHECK") -> OK | F7: #,##0.00
A8: KPI-07 | B8: Units per Order | C8: =IF(COUNTIFS(Clean_Data!$I$2:$I$500,"Paid")=0,0,SUMIFS(Clean_Data!$F$2:$F$500,Clean_Data!$I$2:$I$500,"Paid")/COUNTIFS(Clean_Data!$I$2:$I$500,"Paid")) -> 1.75 | D8: 1.75 | E8: =IF(ABS(C8-D8)<0.001,"OK","CHECK") -> OK | F8: 0.00
A9: KPI-08 | B9: Payment Success Rate | C9: =IF(COUNTIFS(Clean_Data!$I$2:$I$500,"Paid")+COUNTIFS(Clean_Data!$I$2:$I$500,"Failed")=0,0,COUNTIFS(Clean_Data!$I$2:$I$500,"Paid")/(COUNTIFS(Clean_Data!$I$2:$I$500,"Paid")+COUNTIFS(Clean_Data!$I$2:$I$500,"Failed"))) -> 0.8 | D9: 0.8 | E9: =IF(ABS(C9-D9)<0.001,"OK","CHECK") -> OK | F9: 0.0%
A10: KPI-09 | B10: Refund Rate | C10: =IF(COUNTIFS(Clean_Data!$I$2:$I$500,"Paid")+COUNTIFS(Clean_Data!$I$2:$I$500,"Refunded")=0,0,COUNTIFS(Clean_Data!$I$2:$I$500,"Refunded")/(COUNTIFS(Clean_Data!$I$2:$I$500,"Paid")+COUNTIFS(Clean_Data!$I$2:$I$500,"Refunded"))) -> 0.2 | D10: 0.2 | E10: =IF(ABS(C10-D10)<0.001,"OK","CHECK") -> OK | F10: 0.0%
A11: KPI-10 | B11: Data Quality Pass Rate | C11: =IF(C14=0,0,C2/C14) -> 0.54545455 | D11: 0.5455 | E11: =IF(ABS(C11-D11)<0.001,"OK","CHECK") -> OK | F11: 0.0%
A13: Helper
A14: Distinct order_ids in Raw_Data | C14: =SUMPRODUCT((Raw_Data!$A$2:$A$13<>"")/COUNTIF(Raw_Data!$A$2:$A$13,Raw_Data!$A$2:$A$13&"")) -> 11
A15: Raw rows | C15: =COUNTA(Raw_Data!$A$2:$A$13) -> 12
A16: Rows in Clean_Data | C16: =COUNTA(Clean_Data!$A$2:$A$500) -> 6
A17: Rows in Quarantine | C17: =COUNTA(Quarantine!$B$2:$B$100) -> 5
A18: Duplicates dropped | C18: =C15-C16-C17 -> 1
A19: Row accounting (raw = clean + quarantine + duplicates) | C19: =IF(C18>=0,"OK","CHECK") -> OK

Sheet DQ_Checks
A1: Check ID | B1: Dimension | C1: Rule | D1: Column(s) | E1: Unit | F1: Max allowed (threshold) | G1: Severity | H1: Rows failed (notebook) | I1: Measured value (notebook) | J1: Status | K1: Escalation action
A2: C1 | B2: Completeness | C2: order_date is not null | D2: order_date | E2: rate | F2: 0 | G2: P1 | H2: 1 | I2: 0.0833 | J2: =IF(I2<=F2,"PASS","FAIL") -> FAIL | K2: =INDEX(Severity_Escalation!$C$2:$C$4,MATCH(G2,Severity_Escalation!$A$2:$A$4,0)) -> BLOCK: stop the dashboard refresh and keep the last good snapshot with a 'data on hold' banner.
A3: C2 | B3: Completeness | C3: city is not null | D3: city | E3: rate | F3: 0.02 | G3: P2 | H3: 1 | I3: 0.0833 | J3: =IF(I3<=F3,"PASS","FAIL") -> FAIL | K3: =INDEX(Severity_Escalation!$C$2:$C$4,MATCH(G3,Severity_Escalation!$A$2:$A$4,0)) -> WARN: publish with a visible data-quality warning; affected rows flagged.
A4: C3 | B4: Completeness | C4: discount_pct is not null (missing is not assumed to be 0) | D4: discount_pct | E4: rate | F4: 0 | G4: P2 | H4: 1 | I4: 0.0833 | J4: =IF(I4<=F4,"PASS","FAIL") -> FAIL | K4: =INDEX(Severity_Escalation!$C$2:$C$4,MATCH(G4,Severity_Escalation!$A$2:$A$4,0)) -> WARN: publish with a visible data-quality warning; affected rows flagged.
A5: C4 | B5: Completeness | C5: all other required columns are not null | D5: order_id, customer_segment, category, quantity, unit_price, payment_status | E5: rate | F5: 0 | G5: P1 | H5: 0 | I5: 0 | J5: =IF(I5<=F5,"PASS","FAIL") -> PASS | K5: =INDEX(Severity_Escalation!$C$2:$C$4,MATCH(G5,Severity_Escalation!$A$2:$A$4,0)) -> BLOCK: stop the dashboard refresh and keep the last good snapshot with a 'data on hold' banner.
A6: U1 | B6: Uniqueness | C6: order_id appears once | D6: order_id | E6: rate | F6: 0 | G6: P1 | H6: 1 | I6: 0.0833 | J6: =IF(I6<=F6,"PASS","FAIL") -> FAIL | K6: =INDEX(Severity_Escalation!$C$2:$C$4,MATCH(G6,Severity_Escalation!$A$2:$A$4,0)) -> BLOCK: stop the dashboard refresh and keep the last good snapshot with a 'data on hold' banner.
A7: U2 | B7: Uniqueness | C7: no fully duplicated rows | D7: all columns | E7: rate | F7: 0 | G7: P1 | H7: 1 | I7: 0.0833 | J7: =IF(I7<=F7,"PASS","FAIL") -> FAIL | K7: =INDEX(Severity_Escalation!$C$2:$C$4,MATCH(G7,Severity_Escalation!$A$2:$A$4,0)) -> BLOCK: stop the dashboard refresh and keep the last good snapshot with a 'data on hold' banner.
A8: V1 | B8: Validity | C8: ISO-formatted order_date is a real date between 2025-01-01 and today | D8: order_date | E8: rate | F8: 0 | G8: P1 | H8: 1 | I8: 0.0833 | J8: =IF(I8<=F8,"PASS","FAIL") -> FAIL | K8: =INDEX(Severity_Escalation!$C$2:$C$4,MATCH(G8,Severity_Escalation!$A$2:$A$4,0)) -> BLOCK: stop the dashboard refresh and keep the last good snapshot with a 'data on hold' banner.
A9: V2 | B9: Validity | C9: quantity is a whole number > 0 | D9: quantity | E9: rate | F9: 0 | G9: P1 | H9: 2 | I9: 0.1667 | J9: =IF(I9<=F9,"PASS","FAIL") -> FAIL | K9: =INDEX(Severity_Escalation!$C$2:$C$4,MATCH(G9,Severity_Escalation!$A$2:$A$4,0)) -> BLOCK: stop the dashboard refresh and keep the last good snapshot with a 'data on hold' banner.
A10: V3 | B10: Validity | C10: unit_price is a non-negative number | D10: unit_price | E10: rate | F10: 0 | G10: P1 | H10: 0 | I10: 0 | J10: =IF(I10<=F10,"PASS","FAIL") -> PASS | K10: =INDEX(Severity_Escalation!$C$2:$C$4,MATCH(G10,Severity_Escalation!$A$2:$A$4,0)) -> BLOCK: stop the dashboard refresh and keep the last good snapshot with a 'data on hold' banner.
A11: V4 | B11: Validity | C11: discount_pct is between 0 and 100 | D11: discount_pct | E11: rate | F11: 0 | G11: P1 | H11: 1 | I11: 0.0833 | J11: =IF(I11<=F11,"PASS","FAIL") -> FAIL | K11: =INDEX(Severity_Escalation!$C$2:$C$4,MATCH(G11,Severity_Escalation!$A$2:$A$4,0)) -> BLOCK: stop the dashboard refresh and keep the last good snapshot with a 'data on hold' banner.
A12: V5 | B12: Validity | C12: category is one of the 3 allowed products | D12: category | E12: rate | F12: 0 | G12: P2 | H12: 0 | I12: 0 | J12: =IF(I12<=F12,"PASS","FAIL") -> PASS | K12: =INDEX(Severity_Escalation!$C$2:$C$4,MATCH(G12,Severity_Escalation!$A$2:$A$4,0)) -> WARN: publish with a visible data-quality warning; affected rows flagged.
A13: V6 | B13: Validity | C13: segment and payment_status map to an allowed value after normalization | D13: customer_segment, payment_status | E13: rate | F13: 0 | G13: P2 | H13: 0 | I13: 0 | J13: =IF(I13<=F13,"PASS","FAIL") -> PASS | K13: =INDEX(Severity_Escalation!$C$2:$C$4,MATCH(G13,Severity_Escalation!$A$2:$A$4,0)) -> WARN: publish with a visible data-quality warning; affected rows flagged.
... A18: K5 | B18: Consistency | C18: no order_id has conflicting versions | D18: order_id | E18: rate | F18: 0 | G18: P1 | H18: 0 | I18: 0 | J18: =IF(I18<=F18,"PASS","FAIL") -> PASS | K18: =INDEX(Severity_Escalation!$C$2:$C$4,MATCH(G18,Severity_Escalation!$A$2:$A$4,0)) -> BLOCK: stop the dashboard refresh and keep the last good snapshot with a 'data on hold' banner.
A19: F1 | B19: Freshness | C19: newest order is at most 2 days old | D19: order_date | E19: days | F19: 2 | G19: P1 | I19: 260 | J19: =IF(I19<=F19,"PASS","FAIL") -> FAIL | K19: =INDEX(Severity_Escalation!$C$2:$C$4,MATCH(G19,Severity_Escalation!$A$2:$A$4,0)) -> BLOCK: stop the dashboard refresh and keep the last good snapshot with a 'data on hold' banner.
B21: Summary
B22: Checks run | C22: =COUNTA(A2:A19) -> 18
B23: Passed | C23: =COUNTIF(J2:J19,"PASS") -> 6
B24: Failed | C24: =COUNTIF(J2:J19,"FAIL") -> 12
B25: P1 failures | C25: =COUNTIFS(G2:G19,"P1",J2:J19,"FAIL") -> 7
B26: Contract verdict | C26: =IF(C25>0,"BLOCK publication","PASS") -> BLOCK publication
B28: Rates are failing rows / total raw rows (12). Freshness is in days since the newest valid order. Edit a threshold in column F and the status recalculates.

Sheet Raw_Data
A1: order_id | B1: order_date | C1: customer_segment | D1: city | E1: category | F1: quantity | G1: unit_price | H1: discount_pct | I1: payment_status
A2: RT-1001 | B2: 2026-01-03 | C2: Student | D2: Chennai | E2: Learning Kit | F2: 2 | G2: 799 | H2: 10 | I2: Paid
A3: RT-1002 | B3: 03/01/2026 | C3: Fresher | D3: Bengaluru | E3: Course Access | F3: 1 | G3: 1499 | H3: 0 | I3: paid
A4: RT-1003 | B4: 2026-01-05 | C4: student | D4: Chennai | E4: Course Access | F4: 1 | G4: 1499 | I4: Pending
A5: RT-1004 | B5: 2026-01-07 | C5: Professional | D5: Hyderabad | E5: Learning Kit | F5: 3 | G5: 799 | H5: 5 | I5: Paid
A6: RT-1004 | B6: 2026-01-07 | C6: Professional | D6: Hyderabad | E6: Learning Kit | F6: 3 | G6: 799 | H6: 5 | I6: Paid
A7: RT-1005 | B7: 2026-01-09 | C7: Fresher | E7: Mentor Session | F7: 1 | G7: 999 | H7: 0 | I7: Failed
A8: RT-1006 | B8: 2026-13-10 | C8: Student | D8: Pune | E8: Learning Kit | F8: -1 | G8: 799 | H8: 10 | I8: Paid
A9: RT-1007 | B9: 2026-01-12 | C9: Professional | D9: Mumbai | E9: Mentor Session | F9: 2 | G9: 999 | H9: 105 | I9: Paid
A10: RT-1008 | B10: 2026-01-14 | C10: Fresher | D10: Bengaluru | E10: Course Access | F10: two | G10: 1499 | H10: 0 | I10: Pending
A11: RT-1009 | B11: 2026-01-16 | C11: Student | D11: Chennai | E11: Learning Kit | F11: 1 | G11: 799 | H11: 0 | I11: Paid
A12: RT-1010 | B12: 2026-01-18 | C12: Professional | D12: Delhi | E12: Course Access | F12: 2 | G12: 1499 | H12: 15 | I12: Refunded
A13: RT-1011 | C13: Student | D13: Kochi | E13: Mentor Session | F13: 1 | G13: 999 | H13: 0 | I13: Paid

Sheet Clean_Data
A1: order_id | B1: order_date | C1: customer_segment | D1: city | E1: category | F1: quantity | G1: unit_price | H1: discount_pct | I1: payment_status | J1: repair_note | K1: gross_value | L1: discount_amount | M1: net_value | O1: Note: to add rows, paste below the last row and copy formulas in K:M down. KPI formulas read rows 2-500.
A2: RT-1001 | B2: 46025 | C2: Student | D2: Chennai | E2: Learning Kit | F2: 2 | G2: 799 | H2: 10 | I2: Paid | K2: =F2*G2 -> 1598 | L2: =K2*H2/100 -> 159.8 | M2: =K2-L2 -> 1438.2
A3: RT-1002 | B3: 46025 | C3: Fresher | D3: Bengaluru | E3: Course Access | F3: 1 | G3: 1499 | H3: 0 | I3: Paid | J3: date repaired from DD/MM/YYYY | K3: =F3*G3 -> 1499 | L3: =K3*H3/100 -> 0 | M3: =K3-L3 -> 1499
A4: RT-1004 | B4: 46029 | C4: Professional | D4: Hyderabad | E4: Learning Kit | F4: 3 | G4: 799 | H4: 5 | I4: Paid | K4: =F4*G4 -> 2397 | L4: =K4*H4/100 -> 119.85 | M4: =K4-L4 -> 2277.15
A5: RT-1005 | B5: 46031 | C5: Fresher | E5: Mentor Session | F5: 1 | G5: 999 | H5: 0 | I5: Failed | J5: city missing (non-blocking) | K5: =F5*G5 -> 999 | L5: =K5*H5/100 -> 0 | M5: =K5-L5 -> 999
A6: RT-1009 | B6: 46038 | C6: Student | D6: Chennai | E6: Learning Kit | F6: 1 | G6: 799 | H6: 0 | I6: Paid | K6: =F6*G6 -> 799 | L6: =K6*H6/100 -> 0 | M6: =K6-L6 -> 799
A7: RT-1010 | B7: 46040 | C7: Professional | D7: Delhi | E7: Course Access | F7: 2 | G7: 1499 | H7: 15 | I7: Refunded | K7: =F7*G7 -> 2998 | L7: =K7*H7/100 -> 449.7 | M7: =K7-L7 -> 2548.3

Sheet Quarantine
A1: source_row | B1: order_id | C1: order_date | D1: customer_segment | E1: city | F1: category | G1: quantity | H1: unit_price | I1: discount_pct | J1: payment_status | K1: reject_reason
A2: 4 | B2: RT-1003 | C2: 2026-01-05 | D2: student | E2: Chennai | F2: Course Access | G2: 1 | H2: 1499 | J2: Pending | K2: discount_pct missing (no justification on file)
A3: 8 | B3: RT-1006 | C3: 2026-13-10 | D3: Student | E3: Pune | F3: Learning Kit | G3: -1 | H3: 799 | I3: 10 | J3: Paid | K3: invalid calendar date '2026-13-10'; quantity must be a whole number > 0 (-1)
A4: 9 | B4: RT-1007 | C4: 2026-01-12 | D4: Professional | E4: Mumbai | F4: Mentor Session | G4: 2 | H4: 999 | I4: 105 | J4: Paid | K4: discount_pct out of range (105)
A5: 10 | B5: RT-1008 | C5: 2026-01-14 | D5: Fresher | E5: Bengaluru | F5: Course Access | G5: two | H5: 1499 | I5: 0 | J5: Pending | K5: quantity not numeric ('two')
A6: 13 | B6: RT-1011 | D6: Student | E6: Kochi | F6: Mentor Session | G6: 1 | H6: 999 | I6: 0 | J6: Paid | K6: missing order_date
A8: Also removed: 1 exact duplicate of RT-1004 (source row 6), dropped before KPI calculation.

Sheet Severity_Escalation
A1: Severity | B1: Meaning | C1: Automatic action | D1: Notify | E1: Response time | F1: Resolution deadline
A2: P1 | B2: Wrong or missing data that changes KPI values or stops them being computed. | C2: BLOCK: stop the dashboard refresh and keep the last good snapshot with a 'data on hold' banner. | D2: Page the Data Platform Owner; email the Decision Owner (Head of Growth & Revenue Ops). | E2: Within 4 business hours | F2: Fix at source, or a written exception signed by the Decision Owner, within 1 business day.
A3: P2 | B3: Quality problem that affects part of the analysis (e.g. a city breakdown) but not headline revenue. | C3: WARN: publish with a visible data-quality warning; affected rows flagged. | D3: Ticket to the source-system owner; summary in the daily DQ digest. | E3: Within 1 business day | F3: Fix within 3 business days.
A4: P3 | B4: Cosmetic or auto-fixable inconsistency (e.g. casing). | C4: AUTO-FIX: normalize in the pipeline and log the change. | D4: Weekly DQ review. | E4: Next weekly review | F4: Fix at source within 2 weeks.
